{
    "articles": [
        {
            "id": 0,
            "title": "Social impact\ninvesting",
            "date": "Mon, 03 Aug 2014 10:07:43 GMT",
            "number": 29,
            "media": "cover-social-impact-investing"
        },
        {
            "id": 1,
            "title": "Future energy\nin cities",
            "date": "Tue, 01 Sep 2014 09:11:28 GMT",
            "number": 30,
            "media": "cover-future-energy-in-cities"
        },
        {
            "id": 2,
            "title": "Hong-Kong\nfor democracy",
            "date": "Mon, 05 Oct 2014 08:59:14 GMT",
            "number": 31,
            "media": "cover-hong-kong-for-democracy",
            "blocks": [
                {
                    "id": 0,
                    "type": "part",
                    "content": {
                        "part": 1,
                        "title": "Why such an\nindignation ?",
                        "duration": 4,
                        "image": "01-part_why-such-an-indignation"
                    }
                },
                {
                    "id": 1,
                    "type": "meta",
                    "content": {
                        "author": "Reuters",
                        "category": "Politics"
                    }
                },
                {
                    "id": 2,
                    "type": "teasing",
                    "content": {
                        "text": "China said it would not tolerate the outside interference in Hong Kong affairs, rejecting as \"thoughtless\" a call from a British minister."
                    }
                },
                {
                    "id": 3,
                    "type": "paragraph",
                    "content": {
                        "text": "Hong Kong returned to [Chinese rule in 1997](/glossary/0) with the guarantee of wide ranging autonomy and an independent judiciary and media under a One country, Two systems formula."
                    }
                },
                {
                    "id": 4,
                    "type": "statement",
                    "content": {
                        "text": "streets demanding fully democratic elections"
                    }
                },
                {
                    "id": 5,
                    "type": "paragraph",
                    "content": {
                        "text": "It is the freest city in China, but every year on the anniversary of the handover from Britain, thousands take to elections amid mounting fears of increased meddling by Beijing's Communist Party leaders."
                    }
                },
                {
                    "id": 6,
                    "type": "pov",
                    "content": {
                        "views": [
                            {
                                "date": "Tue, 29 Sep 2014 14:09:53 GMT",
                                "author": "Reuters",
                                "text": "British Forign Office minister Hugo Swire, called for full universal suffrage."
                            },
                            {
                                "author": "BBC News",
                                "text": "“Hong Kong's internal affairs will not brook any interference by outside forces.”"
                            }
                        ]
                    }
                },
                {
                    "id": 7,
                    "type": "subtitle",
                    "content": {
                        "text": "The government"
                    }
                },
                {
                    "id": 8,
                    "type": "paragraph",
                    "content": {
                        "text": "Instead, Zhang said candidates could only be selected by a broadly representative nominating committee.\n\nHis statement is expected to fuel a pro-democracy movement that is threatening to shut-down Hong Kong's central financial district next July unless the government introduces changes."
                    }
                },
                {
                    "id": 9,
                    "type": "figure",
                    "content": {
                        "image": "zhang-xiaoming",
                        "person": "Zhang Xiaoming",
                        "date": "Tue, 29 Sep 2014 13:22:41 GMT",
                        "text": "Ruled out open nominations for candidates for 2017, saying it was against the Basic Law."
                    }
                },
                {
                    "id": 10,
                    "type": "subtitle",
                    "content": {
                        "text": "The election in 2017"
                    }
                },
                {
                    "id": 11,
                    "type": "paragraph",
                    "content": {
                        "text": "Will still be the most far-reaching version of democracy on Chinese soil. But analysts say Beijing's hardening stance suggest a continuing conservatism towards significant political reforms under new leader Xi Jinping."
                    }
                },
                {
                    "id": 12,
                    "type": "aside",
                    "content": {
                        "text": "The guarantees over the territory's autonomy and the individual rights and freedoms are enshrined in the Hong Kong"
                    }
                },
                {
                    "id": 13,
                    "type": "paragraph",
                    "content": {
                        "text": "His statement is expected to fuel a pro-democracy movement that is threatening to shut-down Hong Kong's central financial district next July unless the government introduces changes."
                    }
                },
                {
                    "id": 14,
                    "type": "keywords",
                    "content": {
                        "keywords": [
                            {
                                "text": "Reuters"
                            },
                            {
                                "text": "BBC News"
                            }
                        ]
                    }
                },
                {
                    "id": 15,
                    "type": "transition",
                    "content": {
                        "transitions": [
                            {
                                "title": "One country,\none autocracy",
                                "teasing": "is what Hong-Kong getting"
                            },
                            {
                                "title": "One country,\ntwo systems",
                                "teasing": "Instead of"
                            }
                        ]
                    }
                },
                {
                    "id": 16,
                    "type": "part",
                    "content": {
                        "part": 2,
                        "title": "The Umbrella\nRevolution",
                        "duration": 4,
                        "image": "02-part_the-umbrella-revolution"
                    }
                },
                {
                    "id": 17,
                    "type": "teasing",
                    "content": {
                        "text": "Protesters flooded the streets of Hong Kong blocking major highway and causing key parts of the famously bustling city to grind to a halt."
                    }
                },
                {
                    "id": 18,
                    "type": "paragraph",
                    "content": {
                        "text": "Who’s out there? The protests were organized in part by the Hong Kong [Federation of Students](/glossary/2), which has since called for an indefinite student strike. Young people are everywhere, but not alone.\n\nThe Hong Kong Professional Teachers Union has joined them with a general strike, as have some professionals."
                    }
                },
                {
                    "id": 19,
                    "type": "subtitle",
                    "content": {
                        "text": "Who’s out there?",
                        "alignment": "center"
                    }
                },
                {
                    "id": 20,
                    "type": "keyfigures",
                    "content": {
                        "title": "The protests",
                        "keys": [
                            {
                                "data": 65,
                                "label": "injuries"
                            },
                            {
                                "data": 800000,
                                "label": "participants"
                            },
                            {
                                "data": 89,
                                "label": "arrestations"
                            }
                        ],
                        "context": "Were organized in part by the Hong Kong\nFederation of Students, which has since\ncalled for an indefinite student strike."
                    }
                },
                {
                    "id": 21,
                    "type": "subtitle",
                    "content": {
                        "text": "Where in Hong-Kong ?",
                        "alignment": "center"
                    }
                },
                {
                    "id": 22,
                    "type": "paragraph",
                    "content": {
                        "text": "The pro-democracy protesters have occupied parts of Hong Kong for more than three weeks. Protesters and police have clashed recently after the government attempted to clear the protest sites.",
                        "alignment": "center"
                    }
                },
                {
                    "id": 23,
                    "type": "image",
                    "content": {
                        "image": "protest-area"
                    }
                },
                {
                    "id": 24,
                    "type": "subtitle",
                    "content": {
                        "text": "What do you want?"
                    }
                },
                {
                    "id": 25,
                    "type": "paragraph",
                    "content": {
                        "text": "As tens of thousands of protesters gather for a sixth day, their demand for the right to choose their leaders in fully democratic elections poses the biggest popular challenge to the ruling [Communist Party](/glossary/1) since Chinese president Xi Jinping took power two years ago.\n\nHe is trying to steer a slowing economy while moving against powerful vested interests in one of the most wide-ranging purges and anti-corruption campaigns since the Communists came to power in 1949."
                    }
                },
                {
                    "id": 26,
                    "type": "pov",
                    "content": {
                        "views": [
                            {
                                "date": "Wed, 30 Sep 2014 11:37:54 GMT",
                                "author": "Reuters",
                                "text": "In the Admiralty district reads, “My parents are crying for me. I am crying for the future.”"
                            },
                            {
                                "author": "BBC News",
                                "text": "“If you want to protest, that is your business. Everyone has their views. But don't involve us.”"
                            }
                        ]
                    }
                },
                {
                    "id": 27,
                    "type": "paragraph",
                    "content": {
                        "text": "Chief Executive Leung Chun-Ying, the embattled head of Hong Kong, said on Sunday that pro-democracy activists have \"almost zero chance\" of winning any concessions from Beijing. Most of the student."
                    }
                },
                {
                    "id": 28,
                    "type": "interview",
                    "content": {
                        "title": "Interview of student",
                        "person": "Fernando Cheung",
                        "subject": "Democracy and universal suffrage may be the ultimate form of political",
                        "thumbnail": "fernando-cheung",
                        "video": "video"
                    }
                },
                {
                    "id": 29,
                    "type": "part",
                    "content": {
                        "part": 3,
                        "title": "The world\nreacting",
                        "duration": 7,
                        "image": "03-part_the-world-reacting"
                    }
                },
                {
                    "id": 30,
                    "type": "teasing",
                    "content": {
                        "text": "How is the government reacting? Not well, especially at first. Here’s a video from the ground of protesters."
                    }
                },
                {
                    "id": 31,
                    "type": "paragraph",
                    "content": {
                        "text": "International awareness of the movement is increasing, and the movement itself is taking shape in a more structured manner. Rallies in support of the protests have occurred in the all world.\n\nHere’s a video from the ground of protesters being teargassed, in attacks that look familiar from [Ferguson](/glossary/3) and helped stoke outrage among citizens:\n\nThe use of pepper spray has been equally alarming, and is reminiscent of previous Occupy protests in the U.S."
                    }
                },
                {
                    "id": 28,
                    "type": "interview",
                    "content": {
                        "title": "Reaction of Tony Yip",
                        "person": "23, research at a science museum",
                        "subject": "“I think the police have betrayed us, They are using violence against ordinary citizens.”",
                        "thumbnail": "tony-yip"
                    }
                },
                {
                    "id": 32,
                    "type": "subtitle",
                    "content": {
                        "text": "Oppressed by chinese politicians"
                    }
                },
                {
                    "id": 33,
                    "type": "paragraph",
                    "content": {
                        "text": "Hong Kong has canceled its annual fireworks celebration of China’s National Day on October 1st, indicating that this thing may continue for the foreseeable future.\n\nBut a hardcore groupe of demonstrators, has kept up the pressure on Hong Kong authoritiers. China rules that gives the city wide-raging autonomy and freedoms not enjoyed in mainland China, with universal suffrage an eventual goal."
                    }
                },
                {
                    "id": 32,
                    "type": "subtitle",
                    "content": {
                        "text": "Supporting by the world"
                    }
                },
                {
                    "id": 33,
                    "type": "paragraph",
                    "content": {
                        "text": "Some chinese protesters have taken to using the “hands up, don’t shoot” imagery of the Michael Brown demonstrations in Ferguson. It’s still a powerful image on the other side of the world.\n\nProtesters in Ferguson have sent a message back:"
                    }
                },
                {
                    "id": 12,
                    "type": "aside",
                    "content": {
                        "text": "Heater, a #Ferguson protester, wearing a sign that says “Stay strong #Hongkong.”"
                    }
                },
                {
                    "id": 33,
                    "type": "paragraph",
                    "content": {
                        "text": "The movement was supported by many occidental politicians."
                    }
                },
                {
                    "id": 9,
                    "type": "figure",
                    "content": {
                        "image": "david-cameron",
                        "person": "David Cameron",
                        "title": "British Prime Minister",
                        "text": "I am deeply concerned about what is happening and I hope this issue can be resolved"
                    }
                },
                {
                    "id": 32,
                    "type": "subtitle",
                    "content": {
                        "text": "Your country is reacting",
                        "alignment": "center"
                    }
                },
                {
                    "id": 34,
                    "type": "implication",
                    "content": {
                        "city": "Paris",
                        "quote": "The covenant is not a measure for Hong Kong’s political reform",
                        "source": "The French government",
                        "image": "image"
                    }
                },
                {
                    "id": 32,
                    "type": "subtitle",
                    "content": {
                        "text": "“Democratic radical” for China"
                    }
                },
                {
                    "id": 33,
                    "type": "paragraph",
                    "content": {
                        "text": "The Chinese Communist Party claimed that the upheavels in Hong Kong were instigated by democratic radicals who had sought support frome “anti-China forces” in Britain and the United States.\n\nIt called them a “gang of people whose hearts belong to colonial rule and who are besotted with Western democracy”."
                    }
                }
            ],
            "parts": [
                {
                    "id": 0,
                    "title": "Why such an indignation ?",
                    "subtitle": "The political challenge of Hong-Kong"
                },
                {
                    "id": 1,
                    "title": "The umbrella revolution",
                    "subtitle": "Young generation in streets"
                },
                {
                    "id": 2,
                    "title": "The world reacting",
                    "subtitle": "Hong-Kong supported by the world"
                },
                {
                    "id": 3,
                    "title": "China mainland don’t care",
                    "subtitle": "China not ready for democracy ?"
                }
            ],
            "definitions": [
                {
                    "id": 0,
                    "title": "Chinese rule in 1997",
                    "text": "The Basic Law was drafted in accordance with the Sino-British Joint Declaration on the Question of Hong-Kong signed between the Chinese and British governments on 19 December 1984 and went into effect on 1 July 1997."
                },
                {
                    "id": 1,
                    "title": "Communist party",
                    "text": "Politically, they are Maoists influenced by Hua Guofeng: They think that the Communist Party is the measure of all things; friends of the Party are worthy of support; enemies of the Party should be opposed at all costs. This hard-line thinking led to the occasional vandalism of Democratic Party political bulletin boards by the indigenous Communists."
                },
                {
                    "id": 2,
                    "title": "Federation of students",
                    "text": "Hong Kong Federation of Students is the biggest student organization in Hong Kong. It consists of the student unions of eight tertiary education institutions. With 51,779 members as of March 2006, the purpose of the HKFS is to promote student movements and to enhance students’ engagement in society."
                },
                {
                    "id": 3,
                    "title": "Ferguson",
                    "text": "Ferguson is a city in St. Louis County, Missouri, United States. On August 9, 2014, an 18-year-old man, Michael Brown, was fatally shot by Darren Wilson, a Ferguson Police Department officer. The incident sparked protests and acts of vandalism in Ferguson and sparked a vigorous debate about law enforcement's relationship with African-Americans."
                }
            ]
        }
    ]
}
